[
  {
    "id": 7523032,
    "slug": "maegsc",
    "title": "java验证码功能",
    "book_id": 988734,
    "book": {
      "id": 988734,
      "type": "Book",
      "slug": "zzab4c",
      "name": "快乐至上",
      "user_id": 1360300,
      "description": "点滴学习，随时记录",
      "creator_id": 1360300,
      "public": 1,
      "items_count": 2,
      "likes_count": 0,
      "watches_count": 1,
      "content_updated_at": "2020-05-26T13:31:14.219Z",
      "updated_at": "2020-05-26T13:31:14.000Z",
      "created_at": "2020-04-29T01:41:14.000Z",
      "namespace": "qingfengxulai-dkls3/zzab4c",
      "user": {
        "id": 1360300,
        "type": "User",
        "login": "qingfengxulai-dkls3",
        "name": "จุ๊บ清风徐来",
        "description": null,
        "avatar_url": "https://cdn.nlark.com/yuque/0/2020/jpeg/anonymous/1588124424624-a85f62e1-faff-4f72-a024-301ebffd1c89.jpeg",
        "books_count": 1,
        "public_books_count": 1,
        "followers_count": 0,
        "following_count": 0,
        "created_at": "2020-04-29T01:40:47.000Z",
        "updated_at": "2020-05-26T10:25:51.000Z",
        "_serializer": "v2.user"
      },
      "_serializer": "v2.book"
    },
    "user_id": 1360300,
    "creator": {
      "id": 1360300,
      "type": "User",
      "login": "qingfengxulai-dkls3",
      "name": "จุ๊บ清风徐来",
      "description": null,
      "avatar_url": "https://cdn.nlark.com/yuque/0/2020/jpeg/anonymous/1588124424624-a85f62e1-faff-4f72-a024-301ebffd1c89.jpeg",
      "books_count": 1,
      "public_books_count": 1,
      "followers_count": 0,
      "following_count": 0,
      "created_at": "2020-04-29T01:40:47.000Z",
      "updated_at": "2020-05-26T10:25:51.000Z",
      "_serializer": "v2.user"
    },
    "format": "lake",
    "body": "\n<br />简单代码：<br />\n<br />\n<br />@GetMapping(\"/verification\")<br />\t@ApiOperation(\"验证码\")<br />\tpublic void verification(HttpServletResponse resp) throws FileNotFoundException, IOException {<br /> int w = 70;<br /> int h = 35;<br /> Random r = new Random();//创建一个新的随机数生成器<br /> BufferedImage image = new BufferedImage(w, h, BufferedImage.TYPE_INT_RGB);<br /> Graphics2D g2 = (Graphics2D) image.getGraphics();<br /> g2.fillRect(0, 0, w, h);<br /> // 向图片中画4个字符<br /> StringBuffer sb = new StringBuffer(6);<br /> for (int i = 0; i < 4; i++) { // 循环四次每次生成一个字符<br /> \tString s = r.nextInt(10) + \"\";// 随机生成一个字母<br /> \tsb.append(s);<br /> \tfloat x = i * 1.0F * w / 4; // 设置当前字符的X轴坐标<br /> \tg2.setColor(Color.BLUE);<br /> \tg2.drawString(s, x, h - 5); // 画图<br /> \t// 增加线条干扰<br /> \tg2.setColor(Color.YELLOW);<br /> \tg2.drawLine(r.nextInt(20), r.nextInt(50), r.nextInt(50), r.nextInt(50));<br /> \tg2.setColor(Color.RED);<br /> \tg2.drawLine(r.nextInt(20), r.nextInt(50), r.nextInt(50), r.nextInt(50));<br /> \tg2.setColor(Color.GREEN);<br /> \tg2.drawLine(r.nextInt(20), r.nextInt(50), r.nextInt(50), r.nextInt(50));<br /> }<br /> ByteArrayOutputStream baos = new ByteArrayOutputStream();<br /> ImageIO.write(image, \"JPEG\", baos);<br /> byte[] byteArray = baos.toByteArray();<br /> // 存放图片验证码 唯一编码<br /> String id = UUID.randomUUID().toString();<br /> redisUtils.hset(\"verification\", id, sb, 1000*60*2);//redis缓存<br /> resp.setHeader(\"RandomUUID\", id);// 返回给前端，无法返回数据，直接添加在header中<br /> resp.setHeader(\"Access-Control-Expose-Headers\", \"RandomUUID\");<br /> resp.getOutputStream().write(byteArray);<br /> resp.setContentType(\"image/jpeg;charset=UTF-8\");<br />\t}<br />\n<br />更新测试！！<br />第5次测试！！<br />第00099啊实打实的测试啊啊啊啊啊！超时间？？？！<br />未完成，测试语雀自动推送github\n",
    "body_draft": "\n<br />简单代码：<br />\n<br />\n<br />@GetMapping(\"/verification\")<br />\t@ApiOperation(\"验证码\")<br />\tpublic void verification(HttpServletResponse resp) throws FileNotFoundException, IOException {<br /> int w = 70;<br /> int h = 35;<br /> Random r = new Random();//创建一个新的随机数生成器<br /> BufferedImage image = new BufferedImage(w, h, BufferedImage.TYPE_INT_RGB);<br /> Graphics2D g2 = (Graphics2D) image.getGraphics();<br /> g2.fillRect(0, 0, w, h);<br /> // 向图片中画4个字符<br /> StringBuffer sb = new StringBuffer(6);<br /> for (int i = 0; i < 4; i++) { // 循环四次每次生成一个字符<br /> \tString s = r.nextInt(10) + \"\";// 随机生成一个字母<br /> \tsb.append(s);<br /> \tfloat x = i * 1.0F * w / 4; // 设置当前字符的X轴坐标<br /> \tg2.setColor(Color.BLUE);<br /> \tg2.drawString(s, x, h - 5); // 画图<br /> \t// 增加线条干扰<br /> \tg2.setColor(Color.YELLOW);<br /> \tg2.drawLine(r.nextInt(20), r.nextInt(50), r.nextInt(50), r.nextInt(50));<br /> \tg2.setColor(Color.RED);<br /> \tg2.drawLine(r.nextInt(20), r.nextInt(50), r.nextInt(50), r.nextInt(50));<br /> \tg2.setColor(Color.GREEN);<br /> \tg2.drawLine(r.nextInt(20), r.nextInt(50), r.nextInt(50), r.nextInt(50));<br /> }<br /> ByteArrayOutputStream baos = new ByteArrayOutputStream();<br /> ImageIO.write(image, \"JPEG\", baos);<br /> byte[] byteArray = baos.toByteArray();<br /> // 存放图片验证码 唯一编码<br /> String id = UUID.randomUUID().toString();<br /> redisUtils.hset(\"verification\", id, sb, 1000*60*2);//redis缓存<br /> resp.setHeader(\"RandomUUID\", id);// 返回给前端，无法返回数据，直接添加在header中<br /> resp.setHeader(\"Access-Control-Expose-Headers\", \"RandomUUID\");<br /> resp.getOutputStream().write(byteArray);<br /> resp.setContentType(\"image/jpeg;charset=UTF-8\");<br />\t}<br />\n<br />更新测试！！<br />第5次测试！！<br />第00099啊实打实的测试啊啊啊啊啊！超时间？？？！<br />未完成，测试语雀自动推送github\n",
    "body_html": "<!doctype html><div class=\"lake-content-editor-core lake-engine lake-typography-classic\" data-lake-element=\"root\"><p data-lake-id=\"a20d224c568e48b9d67847a2c66a8c01_p_0\" style=\"font-size: 14px; color: rgb(38, 38, 38); line-height: 1.74; letter-spacing: 0.05em; outline-style: none; overflow-wrap: break-word; margin: 0px;\"><br></p><p data-lake-id=\"2c9ddf6595c8d4b6bb03327d9be4d64d\" style=\"font-size: 14px; color: rgb(38, 38, 38); line-height: 1.74; letter-spacing: 0.05em; outline-style: none; overflow-wrap: break-word; margin: 0px;\">简单代码：</p><p data-lake-id=\"258ed2a8cb9bd7406470bf6ecf50309f\" style=\"font-size: 14px; color: rgb(38, 38, 38); line-height: 1.74; letter-spacing: 0.05em; outline-style: none; overflow-wrap: break-word; margin: 0px;\"><br></p><p data-lake-id=\"c608ec21c0171ff780f9fb473a0225a6\" style=\"font-size: 14px; color: rgb(38, 38, 38); line-height: 1.74; letter-spacing: 0.05em; outline-style: none; overflow-wrap: break-word; margin: 0px;\"><br></p><p data-lake-id=\"29711570889df73b3cf85fb45fd20baf\" style=\"font-size: 14px; color: rgb(38, 38, 38); line-height: 1.74; letter-spacing: 0.05em; outline-style: none; overflow-wrap: break-word; margin: 0px;\">@GetMapping(\"/verification\")</p><p data-lake-id=\"ea1585f73c1258ac0f194de8031ce97d\" style=\"font-size: 14px; color: rgb(38, 38, 38); line-height: 1.74; letter-spacing: 0.05em; outline-style: none; overflow-wrap: break-word; margin: 0px;\">\t@ApiOperation(\"验证码\")</p><p data-lake-id=\"6a4b043f4d494e63ab2f6f5a81e19e13\" style=\"font-size: 14px; color: rgb(38, 38, 38); line-height: 1.74; letter-spacing: 0.05em; outline-style: none; overflow-wrap: break-word; margin: 0px;\">\tpublic void verification(HttpServletResponse resp) throws FileNotFoundException, IOException {</p><p data-lake-id=\"be765dc1c9d9d5bb89cda7cca143fefb\" style=\"font-size: 14px; color: rgb(38, 38, 38); line-height: 1.74; letter-spacing: 0.05em; outline-style: none; overflow-wrap: break-word; margin: 0px;\">&nbsp;int w = 70;</p><p data-lake-id=\"402616d49fe0e6b98cb632704b697754\" style=\"font-size: 14px; color: rgb(38, 38, 38); line-height: 1.74; letter-spacing: 0.05em; outline-style: none; overflow-wrap: break-word; margin: 0px;\">&nbsp;int h = 35;</p><p data-lake-id=\"b47151e3f0db2d9d6aad1614e492d8d7\" style=\"font-size: 14px; color: rgb(38, 38, 38); line-height: 1.74; letter-spacing: 0.05em; outline-style: none; overflow-wrap: break-word; margin: 0px;\">&nbsp;Random r = new Random();//创建一个新的随机数生成器</p><p data-lake-id=\"edbc3598eb08b351e6651b12de933064\" style=\"font-size: 14px; color: rgb(38, 38, 38); line-height: 1.74; letter-spacing: 0.05em; outline-style: none; overflow-wrap: break-word; margin: 0px;\">&nbsp;BufferedImage image = new BufferedImage(w, h, BufferedImage.TYPE_INT_RGB);</p><p data-lake-id=\"6216a1232b24e63a2adc430cf8e40a53\" style=\"font-size: 14px; color: rgb(38, 38, 38); line-height: 1.74; letter-spacing: 0.05em; outline-style: none; overflow-wrap: break-word; margin: 0px;\">&nbsp;Graphics2D g2 = (Graphics2D) image.getGraphics();</p><p data-lake-id=\"9d6de7a56d3dcbb318b4d85416e19c8a\" style=\"font-size: 14px; color: rgb(38, 38, 38); line-height: 1.74; letter-spacing: 0.05em; outline-style: none; overflow-wrap: break-word; margin: 0px;\">&nbsp;g2.fillRect(0, 0, w, h);</p><p data-lake-id=\"0179f5f8499ba3ac4bde857a578e8123\" style=\"font-size: 14px; color: rgb(38, 38, 38); line-height: 1.74; letter-spacing: 0.05em; outline-style: none; overflow-wrap: break-word; margin: 0px;\">&nbsp;// 向图片中画4个字符</p><p data-lake-id=\"02316165639367f2e45246ef07effc30\" style=\"font-size: 14px; color: rgb(38, 38, 38); line-height: 1.74; letter-spacing: 0.05em; outline-style: none; overflow-wrap: break-word; margin: 0px;\">&nbsp;StringBuffer sb = new StringBuffer(6);</p><p data-lake-id=\"ab5b5fb3dc9b15fb4425e892ad5fa94b\" style=\"font-size: 14px; color: rgb(38, 38, 38); line-height: 1.74; letter-spacing: 0.05em; outline-style: none; overflow-wrap: break-word; margin: 0px;\">&nbsp;for (int i = 0; i &lt; 4; i++) { // 循环四次每次生成一个字符</p><p data-lake-id=\"5147cf3792b3d360d780c58aa2cbeaa7\" style=\"font-size: 14px; color: rgb(38, 38, 38); line-height: 1.74; letter-spacing: 0.05em; outline-style: none; overflow-wrap: break-word; margin: 0px;\">&nbsp;\tString s = r.nextInt(10) + \"\";// 随机生成一个字母</p><p data-lake-id=\"7c05387eebec8d0c168336d6f0d7dc62\" style=\"font-size: 14px; color: rgb(38, 38, 38); line-height: 1.74; letter-spacing: 0.05em; outline-style: none; overflow-wrap: break-word; margin: 0px;\">&nbsp;\tsb.append(s);</p><p data-lake-id=\"86136ab6b8e0cc6b6ce3f2d4c3221288\" style=\"font-size: 14px; color: rgb(38, 38, 38); line-height: 1.74; letter-spacing: 0.05em; outline-style: none; overflow-wrap: break-word; margin: 0px;\">&nbsp;\tfloat x = i * 1.0F * w / 4; // 设置当前字符的X轴坐标</p><p data-lake-id=\"cd41966c8eac038ba8efa9676def1013\" style=\"font-size: 14px; color: rgb(38, 38, 38); line-height: 1.74; letter-spacing: 0.05em; outline-style: none; overflow-wrap: break-word; margin: 0px;\">&nbsp;\tg2.setColor(Color.BLUE);</p><p data-lake-id=\"7f7f2a6a77662515bd878046dcb25a7e\" style=\"font-size: 14px; color: rgb(38, 38, 38); line-height: 1.74; letter-spacing: 0.05em; outline-style: none; overflow-wrap: break-word; margin: 0px;\">&nbsp;\tg2.drawString(s, x, h - 5); // 画图</p><p data-lake-id=\"a4dbddf5d50f184546eee5d9b8b2c5ff\" style=\"font-size: 14px; color: rgb(38, 38, 38); line-height: 1.74; letter-spacing: 0.05em; outline-style: none; overflow-wrap: break-word; margin: 0px;\">&nbsp;\t// 增加线条干扰</p><p data-lake-id=\"801cb1d780cf1ee6fd405dda84ac16b2\" style=\"font-size: 14px; color: rgb(38, 38, 38); line-height: 1.74; letter-spacing: 0.05em; outline-style: none; overflow-wrap: break-word; margin: 0px;\">&nbsp;\tg2.setColor(Color.YELLOW);</p><p data-lake-id=\"4a05dc249499347aff19b46645eabe58\" style=\"font-size: 14px; color: rgb(38, 38, 38); line-height: 1.74; letter-spacing: 0.05em; outline-style: none; overflow-wrap: break-word; margin: 0px;\">&nbsp;\tg2.drawLine(r.nextInt(20), r.nextInt(50), r.nextInt(50), r.nextInt(50));</p><p data-lake-id=\"4f9b307067ff643291bce052c39fac8c\" style=\"font-size: 14px; color: rgb(38, 38, 38); line-height: 1.74; letter-spacing: 0.05em; outline-style: none; overflow-wrap: break-word; margin: 0px;\">&nbsp;\tg2.setColor(Color.RED);</p><p data-lake-id=\"23be61e738a1314d3ff6697ae7f8fb83\" style=\"font-size: 14px; color: rgb(38, 38, 38); line-height: 1.74; letter-spacing: 0.05em; outline-style: none; overflow-wrap: break-word; margin: 0px;\">&nbsp;\tg2.drawLine(r.nextInt(20), r.nextInt(50), r.nextInt(50), r.nextInt(50));</p><p data-lake-id=\"dfbadacfab7976dbca3686b230222291\" style=\"font-size: 14px; color: rgb(38, 38, 38); line-height: 1.74; letter-spacing: 0.05em; outline-style: none; overflow-wrap: break-word; margin: 0px;\">&nbsp;\tg2.setColor(Color.GREEN);</p><p data-lake-id=\"f9591e5a7a37c5441a403ceec2316314\" style=\"font-size: 14px; color: rgb(38, 38, 38); line-height: 1.74; letter-spacing: 0.05em; outline-style: none; overflow-wrap: break-word; margin: 0px;\">&nbsp;\tg2.drawLine(r.nextInt(20), r.nextInt(50), r.nextInt(50), r.nextInt(50));</p><p data-lake-id=\"5e37e29b8d5c0e017c71af4f0f933793\" style=\"font-size: 14px; color: rgb(38, 38, 38); line-height: 1.74; letter-spacing: 0.05em; outline-style: none; overflow-wrap: break-word; margin: 0px;\">&nbsp;}</p><p data-lake-id=\"ed469e19f4fcf2d467b4d1a3aae7c803\" style=\"font-size: 14px; color: rgb(38, 38, 38); line-height: 1.74; letter-spacing: 0.05em; outline-style: none; overflow-wrap: break-word; margin: 0px;\">&nbsp;ByteArrayOutputStream baos = new ByteArrayOutputStream();</p><p data-lake-id=\"589361a8241003acbbdfcd4896ac97b3\" style=\"font-size: 14px; color: rgb(38, 38, 38); line-height: 1.74; letter-spacing: 0.05em; outline-style: none; overflow-wrap: break-word; margin: 0px;\">&nbsp;ImageIO.write(image, \"JPEG\", baos);</p><p data-lake-id=\"972872c90d8fceaab3495681b1874723\" style=\"font-size: 14px; color: rgb(38, 38, 38); line-height: 1.74; letter-spacing: 0.05em; outline-style: none; overflow-wrap: break-word; margin: 0px;\">&nbsp;byte[] byteArray = baos.toByteArray();</p><p data-lake-id=\"1810f27af42a58516e2a26fbe0e71a8c\" style=\"font-size: 14px; color: rgb(38, 38, 38); line-height: 1.74; letter-spacing: 0.05em; outline-style: none; overflow-wrap: break-word; margin: 0px;\">&nbsp;// 存放图片验证码 唯一编码</p><p data-lake-id=\"dafbb6e50a1743e61f95ac37d4f9d976\" style=\"font-size: 14px; color: rgb(38, 38, 38); line-height: 1.74; letter-spacing: 0.05em; outline-style: none; overflow-wrap: break-word; margin: 0px;\">&nbsp;String id = UUID.randomUUID().toString();</p><p data-lake-id=\"3b2b2020cf15ec3671366933adca7fd1\" style=\"font-size: 14px; color: rgb(38, 38, 38); line-height: 1.74; letter-spacing: 0.05em; outline-style: none; overflow-wrap: break-word; margin: 0px;\">&nbsp;redisUtils.hset(\"verification\", id, sb, 1000*60*2);//redis缓存</p><p data-lake-id=\"ab782e1298f367119bfa8ab5ca973e58\" style=\"font-size: 14px; color: rgb(38, 38, 38); line-height: 1.74; letter-spacing: 0.05em; outline-style: none; overflow-wrap: break-word; margin: 0px;\">&nbsp;resp.setHeader(\"RandomUUID\", id);// 返回给前端，无法返回数据，直接添加在header中</p><p data-lake-id=\"361f095322450e649952db67f9aced1f\" style=\"font-size: 14px; color: rgb(38, 38, 38); line-height: 1.74; letter-spacing: 0.05em; outline-style: none; overflow-wrap: break-word; margin: 0px;\">&nbsp;resp.setHeader(\"Access-Control-Expose-Headers\", \"RandomUUID\");</p><p data-lake-id=\"d16601f6fcc65223862b92fcf69ab471\" style=\"font-size: 14px; color: rgb(38, 38, 38); line-height: 1.74; letter-spacing: 0.05em; outline-style: none; overflow-wrap: break-word; margin: 0px;\">&nbsp;resp.getOutputStream().write(byteArray);</p><p data-lake-id=\"792689917b10c261123e183ff809ccf1\" style=\"font-size: 14px; color: rgb(38, 38, 38); line-height: 1.74; letter-spacing: 0.05em; outline-style: none; overflow-wrap: break-word; margin: 0px;\">&nbsp;resp.setContentType(\"image/jpeg;charset=UTF-8\");</p><p data-lake-id=\"5d6f89112fa0fcb9c68f75c520d96e00\" style=\"font-size: 14px; color: rgb(38, 38, 38); line-height: 1.74; letter-spacing: 0.05em; outline-style: none; overflow-wrap: break-word; margin: 0px;\">\t}</p><p data-lake-id=\"d67638ad1eabfd0846359ddbaac62523\" style=\"font-size: 14px; color: rgb(38, 38, 38); line-height: 1.74; letter-spacing: 0.05em; outline-style: none; overflow-wrap: break-word; margin: 0px;\"><br></p><p data-lake-id=\"cbe53f2c6478aaa3c522bfcbb2db8153\" style=\"font-size: 14px; color: rgb(38, 38, 38); line-height: 1.74; letter-spacing: 0.05em; outline-style: none; overflow-wrap: break-word; margin: 0px;\">更新测试！！</p><p data-lake-id=\"106843c25b92bf7e053e18fb4fd9c695\" style=\"font-size: 14px; color: rgb(38, 38, 38); line-height: 1.74; letter-spacing: 0.05em; outline-style: none; overflow-wrap: break-word; margin: 0px;\">第5次测试！！</p><p data-lake-id=\"0bb8f4da72972130a46b1c816768ff40\" style=\"font-size: 14px; color: rgb(38, 38, 38); line-height: 1.74; letter-spacing: 0.05em; outline-style: none; overflow-wrap: break-word; margin: 0px;\"><span>第00099啊实打实的测试啊啊啊啊啊！超时间？？？！</span></p><p data-lake-id=\"63bed550ac85f9d641bf09ac4e3e3d32\" style=\"font-size: 14px; color: rgb(38, 38, 38); line-height: 1.74; letter-spacing: 0.05em; outline-style: none; overflow-wrap: break-word; margin: 0px;\">未完成，测试语雀自动推送github</p></div>",
    "body_lake": "<!doctype lake><meta name=\"doc-version\" content=\"1\" /><meta name=\"viewport\" content=\"fixed\" /><meta name=\"typography\" content=\"classic\" /><p data-lake-id=\"a20d224c568e48b9d67847a2c66a8c01_p_0\"><br /></p><p data-lake-id=\"2c9ddf6595c8d4b6bb03327d9be4d64d\">简单代码：</p><p data-lake-id=\"258ed2a8cb9bd7406470bf6ecf50309f\"><br /></p><p data-lake-id=\"c608ec21c0171ff780f9fb473a0225a6\"><br /></p><p data-lake-id=\"29711570889df73b3cf85fb45fd20baf\">@GetMapping(&quot;/verification&quot;)</p><p data-lake-id=\"ea1585f73c1258ac0f194de8031ce97d\">\t@ApiOperation(&quot;验证码&quot;)</p><p data-lake-id=\"6a4b043f4d494e63ab2f6f5a81e19e13\">\tpublic void verification(HttpServletResponse resp) throws FileNotFoundException, IOException {</p><p data-lake-id=\"be765dc1c9d9d5bb89cda7cca143fefb\"> int w = 70;</p><p data-lake-id=\"402616d49fe0e6b98cb632704b697754\"> int h = 35;</p><p data-lake-id=\"b47151e3f0db2d9d6aad1614e492d8d7\"> Random r = new Random();//创建一个新的随机数生成器</p><p data-lake-id=\"edbc3598eb08b351e6651b12de933064\"> BufferedImage image = new BufferedImage(w, h, BufferedImage.TYPE_INT_RGB);</p><p data-lake-id=\"6216a1232b24e63a2adc430cf8e40a53\"> Graphics2D g2 = (Graphics2D) image.getGraphics();</p><p data-lake-id=\"9d6de7a56d3dcbb318b4d85416e19c8a\"> g2.fillRect(0, 0, w, h);</p><p data-lake-id=\"0179f5f8499ba3ac4bde857a578e8123\"> // 向图片中画4个字符</p><p data-lake-id=\"02316165639367f2e45246ef07effc30\"> StringBuffer sb = new StringBuffer(6);</p><p data-lake-id=\"ab5b5fb3dc9b15fb4425e892ad5fa94b\"> for (int i = 0; i &lt; 4; i++) { // 循环四次每次生成一个字符</p><p data-lake-id=\"5147cf3792b3d360d780c58aa2cbeaa7\"> \tString s = r.nextInt(10) + &quot;&quot;;// 随机生成一个字母</p><p data-lake-id=\"7c05387eebec8d0c168336d6f0d7dc62\"> \tsb.append(s);</p><p data-lake-id=\"86136ab6b8e0cc6b6ce3f2d4c3221288\"> \tfloat x = i * 1.0F * w / 4; // 设置当前字符的X轴坐标</p><p data-lake-id=\"cd41966c8eac038ba8efa9676def1013\"> \tg2.setColor(Color.BLUE);</p><p data-lake-id=\"7f7f2a6a77662515bd878046dcb25a7e\"> \tg2.drawString(s, x, h - 5); // 画图</p><p data-lake-id=\"a4dbddf5d50f184546eee5d9b8b2c5ff\"> \t// 增加线条干扰</p><p data-lake-id=\"801cb1d780cf1ee6fd405dda84ac16b2\"> \tg2.setColor(Color.YELLOW);</p><p data-lake-id=\"4a05dc249499347aff19b46645eabe58\"> \tg2.drawLine(r.nextInt(20), r.nextInt(50), r.nextInt(50), r.nextInt(50));</p><p data-lake-id=\"4f9b307067ff643291bce052c39fac8c\"> \tg2.setColor(Color.RED);</p><p data-lake-id=\"23be61e738a1314d3ff6697ae7f8fb83\"> \tg2.drawLine(r.nextInt(20), r.nextInt(50), r.nextInt(50), r.nextInt(50));</p><p data-lake-id=\"dfbadacfab7976dbca3686b230222291\"> \tg2.setColor(Color.GREEN);</p><p data-lake-id=\"f9591e5a7a37c5441a403ceec2316314\"> \tg2.drawLine(r.nextInt(20), r.nextInt(50), r.nextInt(50), r.nextInt(50));</p><p data-lake-id=\"5e37e29b8d5c0e017c71af4f0f933793\"> }</p><p data-lake-id=\"ed469e19f4fcf2d467b4d1a3aae7c803\"> ByteArrayOutputStream baos = new ByteArrayOutputStream();</p><p data-lake-id=\"589361a8241003acbbdfcd4896ac97b3\"> ImageIO.write(image, &quot;JPEG&quot;, baos);</p><p data-lake-id=\"972872c90d8fceaab3495681b1874723\"> byte[] byteArray = baos.toByteArray();</p><p data-lake-id=\"1810f27af42a58516e2a26fbe0e71a8c\"> // 存放图片验证码 唯一编码</p><p data-lake-id=\"dafbb6e50a1743e61f95ac37d4f9d976\"> String id = UUID.randomUUID().toString();</p><p data-lake-id=\"3b2b2020cf15ec3671366933adca7fd1\"> redisUtils.hset(&quot;verification&quot;, id, sb, 1000*60*2);//redis缓存</p><p data-lake-id=\"ab782e1298f367119bfa8ab5ca973e58\"> resp.setHeader(&quot;RandomUUID&quot;, id);// 返回给前端，无法返回数据，直接添加在header中</p><p data-lake-id=\"361f095322450e649952db67f9aced1f\"> resp.setHeader(&quot;Access-Control-Expose-Headers&quot;, &quot;RandomUUID&quot;);</p><p data-lake-id=\"d16601f6fcc65223862b92fcf69ab471\"> resp.getOutputStream().write(byteArray);</p><p data-lake-id=\"792689917b10c261123e183ff809ccf1\"> resp.setContentType(&quot;image/jpeg;charset=UTF-8&quot;);</p><p data-lake-id=\"5d6f89112fa0fcb9c68f75c520d96e00\">\t}</p><p data-lake-id=\"d67638ad1eabfd0846359ddbaac62523\"><br /></p><p data-lake-id=\"cbe53f2c6478aaa3c522bfcbb2db8153\">更新测试！！</p><p data-lake-id=\"106843c25b92bf7e053e18fb4fd9c695\">第5次测试！！</p><p data-lake-id=\"0bb8f4da72972130a46b1c816768ff40\"><span>第00099啊实打实的测试啊啊啊啊啊！超时间？？？！</span></p><p data-lake-id=\"63bed550ac85f9d641bf09ac4e3e3d32\">未完成，测试语雀自动推送github</p>",
    "body_draft_lake": "<!doctype lake><meta name=\"doc-version\" content=\"1\" /><meta name=\"viewport\" content=\"fixed\" /><meta name=\"typography\" content=\"classic\" /><p data-lake-id=\"a20d224c568e48b9d67847a2c66a8c01_p_0\"><br /></p><p data-lake-id=\"2c9ddf6595c8d4b6bb03327d9be4d64d\">简单代码：</p><p data-lake-id=\"258ed2a8cb9bd7406470bf6ecf50309f\"><br /></p><p data-lake-id=\"c608ec21c0171ff780f9fb473a0225a6\"><br /></p><p data-lake-id=\"29711570889df73b3cf85fb45fd20baf\">@GetMapping(&quot;/verification&quot;)</p><p data-lake-id=\"ea1585f73c1258ac0f194de8031ce97d\">\t@ApiOperation(&quot;验证码&quot;)</p><p data-lake-id=\"6a4b043f4d494e63ab2f6f5a81e19e13\">\tpublic void verification(HttpServletResponse resp) throws FileNotFoundException, IOException {</p><p data-lake-id=\"be765dc1c9d9d5bb89cda7cca143fefb\"> int w = 70;</p><p data-lake-id=\"402616d49fe0e6b98cb632704b697754\"> int h = 35;</p><p data-lake-id=\"b47151e3f0db2d9d6aad1614e492d8d7\"> Random r = new Random();//创建一个新的随机数生成器</p><p data-lake-id=\"edbc3598eb08b351e6651b12de933064\"> BufferedImage image = new BufferedImage(w, h, BufferedImage.TYPE_INT_RGB);</p><p data-lake-id=\"6216a1232b24e63a2adc430cf8e40a53\"> Graphics2D g2 = (Graphics2D) image.getGraphics();</p><p data-lake-id=\"9d6de7a56d3dcbb318b4d85416e19c8a\"> g2.fillRect(0, 0, w, h);</p><p data-lake-id=\"0179f5f8499ba3ac4bde857a578e8123\"> // 向图片中画4个字符</p><p data-lake-id=\"02316165639367f2e45246ef07effc30\"> StringBuffer sb = new StringBuffer(6);</p><p data-lake-id=\"ab5b5fb3dc9b15fb4425e892ad5fa94b\"> for (int i = 0; i &lt; 4; i++) { // 循环四次每次生成一个字符</p><p data-lake-id=\"5147cf3792b3d360d780c58aa2cbeaa7\"> \tString s = r.nextInt(10) + &quot;&quot;;// 随机生成一个字母</p><p data-lake-id=\"7c05387eebec8d0c168336d6f0d7dc62\"> \tsb.append(s);</p><p data-lake-id=\"86136ab6b8e0cc6b6ce3f2d4c3221288\"> \tfloat x = i * 1.0F * w / 4; // 设置当前字符的X轴坐标</p><p data-lake-id=\"cd41966c8eac038ba8efa9676def1013\"> \tg2.setColor(Color.BLUE);</p><p data-lake-id=\"7f7f2a6a77662515bd878046dcb25a7e\"> \tg2.drawString(s, x, h - 5); // 画图</p><p data-lake-id=\"a4dbddf5d50f184546eee5d9b8b2c5ff\"> \t// 增加线条干扰</p><p data-lake-id=\"801cb1d780cf1ee6fd405dda84ac16b2\"> \tg2.setColor(Color.YELLOW);</p><p data-lake-id=\"4a05dc249499347aff19b46645eabe58\"> \tg2.drawLine(r.nextInt(20), r.nextInt(50), r.nextInt(50), r.nextInt(50));</p><p data-lake-id=\"4f9b307067ff643291bce052c39fac8c\"> \tg2.setColor(Color.RED);</p><p data-lake-id=\"23be61e738a1314d3ff6697ae7f8fb83\"> \tg2.drawLine(r.nextInt(20), r.nextInt(50), r.nextInt(50), r.nextInt(50));</p><p data-lake-id=\"dfbadacfab7976dbca3686b230222291\"> \tg2.setColor(Color.GREEN);</p><p data-lake-id=\"f9591e5a7a37c5441a403ceec2316314\"> \tg2.drawLine(r.nextInt(20), r.nextInt(50), r.nextInt(50), r.nextInt(50));</p><p data-lake-id=\"5e37e29b8d5c0e017c71af4f0f933793\"> }</p><p data-lake-id=\"ed469e19f4fcf2d467b4d1a3aae7c803\"> ByteArrayOutputStream baos = new ByteArrayOutputStream();</p><p data-lake-id=\"589361a8241003acbbdfcd4896ac97b3\"> ImageIO.write(image, &quot;JPEG&quot;, baos);</p><p data-lake-id=\"972872c90d8fceaab3495681b1874723\"> byte[] byteArray = baos.toByteArray();</p><p data-lake-id=\"1810f27af42a58516e2a26fbe0e71a8c\"> // 存放图片验证码 唯一编码</p><p data-lake-id=\"dafbb6e50a1743e61f95ac37d4f9d976\"> String id = UUID.randomUUID().toString();</p><p data-lake-id=\"3b2b2020cf15ec3671366933adca7fd1\"> redisUtils.hset(&quot;verification&quot;, id, sb, 1000*60*2);//redis缓存</p><p data-lake-id=\"ab782e1298f367119bfa8ab5ca973e58\"> resp.setHeader(&quot;RandomUUID&quot;, id);// 返回给前端，无法返回数据，直接添加在header中</p><p data-lake-id=\"361f095322450e649952db67f9aced1f\"> resp.setHeader(&quot;Access-Control-Expose-Headers&quot;, &quot;RandomUUID&quot;);</p><p data-lake-id=\"d16601f6fcc65223862b92fcf69ab471\"> resp.getOutputStream().write(byteArray);</p><p data-lake-id=\"792689917b10c261123e183ff809ccf1\"> resp.setContentType(&quot;image/jpeg;charset=UTF-8&quot;);</p><p data-lake-id=\"5d6f89112fa0fcb9c68f75c520d96e00\">\t}</p><p data-lake-id=\"d67638ad1eabfd0846359ddbaac62523\"><br /></p><p data-lake-id=\"cbe53f2c6478aaa3c522bfcbb2db8153\">更新测试！！</p><p data-lake-id=\"106843c25b92bf7e053e18fb4fd9c695\">第5次测试！！</p><p data-lake-id=\"0bb8f4da72972130a46b1c816768ff40\"><span>第00099啊实打实的测试啊啊啊啊啊！超时间？？？！</span></p><p data-lake-id=\"63bed550ac85f9d641bf09ac4e3e3d32\">未完成，测试语雀自动推送github</p>",
    "public": 1,
    "status": 1,
    "view_status": 0,
    "read_status": 1,
    "likes_count": 0,
    "comments_count": 0,
    "content_updated_at": "2020-05-26T13:27:56.000Z",
    "deleted_at": null,
    "created_at": "2020-05-26T13:23:12.000Z",
    "updated_at": "2020-05-26T13:31:14.000Z",
    "published_at": "2020-05-26T13:31:14.000Z",
    "first_published_at": "2020-05-26T13:23:12.000Z",
    "word_count": 288,
    "cover": null,
    "description": "简单代码：@GetMapping(\"/verification\")\t@ApiOperation(\"验证码\")\tpublic void verification(HttpServletResponse resp) throws FileNotFoundException, IOException...",
    "custom_description": null,
    "hits": 0,
    "_serializer": "v2.doc_detail"
  },
  {
    "id": 6554133,
    "slug": "chrh36",
    "title": "生活趣事",
    "book_id": 988734,
    "book": {
      "id": 988734,
      "type": "Book",
      "slug": "zzab4c",
      "name": "快乐至上",
      "user_id": 1360300,
      "description": "点滴学习，随时记录",
      "creator_id": 1360300,
      "public": 1,
      "items_count": 2,
      "likes_count": 0,
      "watches_count": 1,
      "content_updated_at": "2020-05-26T13:31:14.219Z",
      "updated_at": "2020-05-26T13:31:14.000Z",
      "created_at": "2020-04-29T01:41:14.000Z",
      "namespace": "qingfengxulai-dkls3/zzab4c",
      "user": {
        "id": 1360300,
        "type": "User",
        "login": "qingfengxulai-dkls3",
        "name": "จุ๊บ清风徐来",
        "description": null,
        "avatar_url": "https://cdn.nlark.com/yuque/0/2020/jpeg/anonymous/1588124424624-a85f62e1-faff-4f72-a024-301ebffd1c89.jpeg",
        "books_count": 1,
        "public_books_count": 1,
        "followers_count": 0,
        "following_count": 0,
        "created_at": "2020-04-29T01:40:47.000Z",
        "updated_at": "2020-05-26T10:25:51.000Z",
        "_serializer": "v2.user"
      },
      "_serializer": "v2.book"
    },
    "user_id": 1360300,
    "creator": {
      "id": 1360300,
      "type": "User",
      "login": "qingfengxulai-dkls3",
      "name": "จุ๊บ清风徐来",
      "description": null,
      "avatar_url": "https://cdn.nlark.com/yuque/0/2020/jpeg/anonymous/1588124424624-a85f62e1-faff-4f72-a024-301ebffd1c89.jpeg",
      "books_count": 1,
      "public_books_count": 1,
      "followers_count": 0,
      "following_count": 0,
      "created_at": "2020-04-29T01:40:47.000Z",
      "updated_at": "2020-05-26T10:25:51.000Z",
      "_serializer": "v2.user"
    },
    "format": "lake",
    "body": "<a name=\"30e8c\"></a>\n#### ![image.png](https://cdn.nlark.com/yuque/0/2019/png/215718/1567507815646-d739438a-8ffd-4107-9d87-130e2104446a.png#align=left&display=inline&height=232&name=image.png&originHeight=1553&originWidth=1080&size=367334&status=done&width=161)\n_插入封面图片，点击图片，设置图片大小_\n<a name=\"K3ibk\"></a>\n#### 关于本书\n插入「表格」\n\n| **书名** | [《菊次郎与佐纪》](https://book.douban.com/subject/25944034/) | **作者** | 北野武日本 |\n| --- | --- | --- | --- |\n| **出版社** | 译林出版社 | **阅读日期** | 2019年2月 |\n| **豆瓣评分** | 8.1 | **我的评分** | ☆☆☆☆ |\n\n\n<a name=\"uLRxc\"></a>\n#### 内容简介\n在此处输入文本<br />你将读到的是北野武的出身、父母、兄弟和家庭的故事。<br />但请放心，这绝非一个自我感觉良好的人写的那种“优良课外读物”。<br />相反，北野武用搞笑到甚至刻薄方式描绘这些人和事，让我们在笑与泪的交织中，看到真情和真实，看到那么多情、柔软的心。\n\n<a name=\"E9053\"></a>\n#### 书摘\n在此处输入文本\n\n- 你将读到的是北野武的出身、父母、兄弟和家庭的故事。\n- 但请放心，这绝非一个自我感觉良好的人写的那种“优良课外读物”。很喜欢这句←方便打标签的状态卡片\n- 相反，北野武用搞笑到甚至刻薄方式描绘这些人和事，让我们在笑与泪的交织中，看到真情和真实，看到那么多情、柔软的心。\n\n<a name=\"vEdHo\"></a>\n#### 读后感\n在此处输入文本\n\n- 你将读到的是北野武的出身、父母、兄弟和家庭的故事。\n- 但请放心，这绝非一个自我感觉良好的人写的那种“优良课外读物”。\n- 相反，北野武用搞笑到甚至刻薄方式描绘这些人和事，让我们在笑与泪的交织中，看到真情和真实，看到那么多情、柔软的心。\n",
    "body_draft": "<a name=\"30e8c\"></a>\n#### ![image.png](https://cdn.nlark.com/yuque/0/2019/png/215718/1567507815646-d739438a-8ffd-4107-9d87-130e2104446a.png#align=left&display=inline&height=232&margin=%5Bobject%20Object%5D&name=image.png&originHeight=1553&originWidth=1080&size=367334&status=done&style=none&width=161)\n_插入封面图片，点击图片，设置图片大小_\n<a name=\"K3ibk\"></a>\n#### 关于本书\n插入「表格」\n\n| **书名** | [《菊次郎与佐纪》](https://book.douban.com/subject/25944034/) | **作者** | 北野武日本 |\n| --- | --- | --- | --- |\n| **出版社** | 译林出版社 | **阅读日期** | 2019年2月 |\n| **豆瓣评分** | 8.1 | **我的评分** | ☆☆☆☆ |\n\n\n\n<a name=\"uLRxc\"></a>\n#### 内容简介\n在此处输入文本<br />你将读到的是北野武的出身、父母、兄弟和家庭的故事。<br />但请放心，这绝非一个自我感觉良好的人写的那种“优良课外读物”。<br />相反，北野武用搞笑到甚至刻薄方式描绘这些人和事，让我们在笑与泪的交织中，看到真情和真实，看到那么多情、柔软的心。\n\n<a name=\"E9053\"></a>\n#### 书摘\n在此处输入文本\n\n- 你将读到的是北野武的出身、父母、兄弟和家庭的故事。\n- 但请放心，这绝非一个自我感觉良好的人写的那种“优良课外读物”。很喜欢这句←方便打标签的状态卡片\n- 相反，北野武用搞笑到甚至刻薄方式描绘这些人和事，让我们在笑与泪的交织中，看到真情和真实，看到那么多情、柔软的心。\n\n\n\n<a name=\"vEdHo\"></a>\n#### 读后感\n在此处输入文本\n\n- 你将读到的是北野武的出身、父母、兄弟和家庭的故事。\n- 但请放心，这绝非一个自我感觉良好的人写的那种“优良课外读物”。\n- 相反，北野武用搞笑到甚至刻薄方式描绘这些人和事，让我们在笑与泪的交织中，看到真情和真实，看到那么多情、柔软的心。\n",
    "body_html": "<!doctype html><div class=\"lake-content-editor-core lake-engine\" data-lake-element=\"root\" data-selection-105911=\"%7B%22path%22%3A%5B%5B3%2C0%2C0%2C0%2C0%5D%2C%5B3%2C1%2C0%2C0%2C1%5D%5D%2C%22uuid%22%3A%22105911%22%2C%22active%22%3Atrue%7D\"><h4 id=\"30e8c\" style=\"text-align: center; padding: 7px 0px; margin: 0px; font-weight: 700; font-size: 16px; line-height: 24px;\"><span data-card-type=\"inline\" data-lake-card=\"image\" class=\"\"><img data-role=\"image\" src=\"https://cdn.nlark.com/yuque/0/2019/png/215718/1567507815646-d739438a-8ffd-4107-9d87-130e2104446a.png\" data-raw-src=\"https://cdn.nlark.com/yuque/0/2019/png/215718/1567507815646-d739438a-8ffd-4107-9d87-130e2104446a.png\" class=\"image lake-drag-image\" alt=\"image.png\" title=\"image.png\" style=\"visibility: visible; width: 161px; height: 232px;\"></span></h4><p style=\"text-align: center; font-size: 14px; color: rgb(38, 38, 38); line-height: 24px; letter-spacing: 0.05em; outline-style: none; overflow-wrap: break-word; margin: 0px;\"><span style=\"color: #8C8C8C;\"><em><span>插入封面图片，点击图片，设置图片大小</span></em></span></p><h4 id=\"K3ibk\" style=\"text-align: left; padding: 7px 0px; margin: 0px; font-weight: 700; font-size: 16px; line-height: 24px;\">关于本书</h4><p style=\"font-size: 14px; color: rgb(38, 38, 38); line-height: 24px; letter-spacing: 0.05em; outline-style: none; overflow-wrap: break-word; margin: 0px;\"><span style=\"color: #8C8C8C;\"><span>插入「表格</span></span><span style=\"color: #8C8C8C;\"><span>」</span></span></p><div data-card-type=\"block\" data-lake-card=\"table\" id=\"yE9oY\"><table class=\"lake-table\" style=\"width: 695px; outline: none; border-collapse: collapse;\"><colgroup><col width=\"80\" span=\"1\"><col width=\"285\" span=\"1\"><col width=\"91\" span=\"1\"><col width=\"238\" span=\"1\"></colgroup><tbody><tr style=\"height: 33px;\"><td style=\"background-color: rgb(82, 196, 26); min-width: 90px; font-size: 14px; white-space: normal; overflow-wrap: break-word; border: 1px solid rgb(217, 217, 217); padding: 4px 8px; cursor: default;\"><span style=\"color: #FFFFFF;\"><strong>书名</strong></span></td><td style=\"background-color: rgb(228, 247, 210); min-width: 90px; font-size: 14px; white-space: normal; overflow-wrap: break-word; border: 1px solid rgb(217, 217, 217); padding: 4px 8px; cursor: default;\"><p style=\"font-size: 14px; color: rgb(38, 38, 38); line-height: 24px; letter-spacing: 0.05em; outline-style: none; overflow-wrap: break-word; margin: 0px;\"><a href=\"https://book.douban.com/subject/25944034/\" target=\"_blank\">《菊次郎与佐纪》</a></p></td><td style=\"background-color: rgb(82, 196, 26); min-width: 90px; font-size: 14px; white-space: normal; overflow-wrap: break-word; border: 1px solid rgb(217, 217, 217); padding: 4px 8px; cursor: default;\"><span style=\"color: #FFFFFF;\"><strong>作者</strong></span></td><td rowspan=\"1\" style=\"background-color: rgb(228, 247, 210); min-width: 90px; font-size: 14px; white-space: normal; overflow-wrap: break-word; border: 1px solid rgb(217, 217, 217); padding: 4px 8px; cursor: default;\"><p style=\"font-size: 14px; color: rgb(38, 38, 38); line-height: 24px; letter-spacing: 0.05em; outline-style: none; overflow-wrap: break-word; margin: 0px;\">北野武<span data-card-type=\"inline\" data-lake-card=\"label\" contenteditable=\"false\"><span class=\"lake-card-label-container\" style=\"background: rgb(212, 238, 252); color: rgb(0, 58, 140); opacity: 1; font-weight: 400; font-size: 12px; overflow: hidden; max-width: 200px; display: inline-block; white-space: nowrap; margin-bottom: -4px; border-radius: 4px; border: none; padding: 2px 5px; text-overflow: ellipsis; line-height: 14px; margin-left: 1px; margin-right: 1px;\">日本</span></span></p></td></tr><tr style=\"height: 33px;\"><td style=\"vertical-align: top; background-color: rgb(82, 196, 26); color: rgb(38, 38, 38); min-width: 90px; font-size: 14px; white-space: normal; overflow-wrap: break-word; border: 1px solid rgb(217, 217, 217); padding: 4px 8px; cursor: default;\"><p style=\"font-size: 14px; color: rgb(38, 38, 38); line-height: 24px; letter-spacing: 0.05em; outline-style: none; overflow-wrap: break-word; margin: 0px;\"><span style=\"color: #FFFFFF;\"><strong>出版社</strong></span></p></td><td style=\"background-color: rgb(228, 247, 210); min-width: 90px; font-size: 14px; white-space: normal; overflow-wrap: break-word; border: 1px solid rgb(217, 217, 217); padding: 4px 8px; cursor: default;\"><p style=\"font-size: 14px; color: rgb(38, 38, 38); line-height: 24px; letter-spacing: 0.05em; outline-style: none; overflow-wrap: break-word; margin: 0px;\"><span class=\"lake-fontsize-10\" data-mce-style=\"font-size: 10px\" style=\"font-size: 13px; line-height: 24px;\">译林出版社</span></p></td><td style=\"background-color: rgb(82, 196, 26); min-width: 90px; font-size: 14px; white-space: normal; overflow-wrap: break-word; border: 1px solid rgb(217, 217, 217); padding: 4px 8px; cursor: default;\"><p style=\"font-size: 14px; color: rgb(38, 38, 38); line-height: 24px; letter-spacing: 0.05em; outline-style: none; overflow-wrap: break-word; margin: 0px;\"><span style=\"color: #FFFFFF;\"><strong>阅读日期</strong></span></p></td><td rowspan=\"1\" style=\"vertical-align: top; background-color: rgb(228, 247, 210); color: rgb(38, 38, 38); min-width: 90px; font-size: 14px; white-space: normal; overflow-wrap: break-word; border: 1px solid rgb(217, 217, 217); padding: 4px 8px; cursor: default;\"><p style=\"font-size: 14px; color: rgb(38, 38, 38); line-height: 24px; letter-spacing: 0.05em; outline-style: none; overflow-wrap: break-word; margin: 0px;\">2019年2月</p></td></tr><tr style=\"height: 33px;\"><td colspan=\"1\" style=\"vertical-align: top; background-color: rgb(82, 196, 26); color: rgb(38, 38, 38); min-width: 90px; font-size: 14px; white-space: normal; overflow-wrap: break-word; border: 1px solid rgb(217, 217, 217); padding: 4px 8px; cursor: default;\"><p style=\"font-size: 14px; color: rgb(38, 38, 38); line-height: 24px; letter-spacing: 0.05em; outline-style: none; overflow-wrap: break-word; margin: 0px;\"><span style=\"color: #FFFFFF;\"><strong>豆瓣评分</strong></span></p></td><td colspan=\"1\" style=\"vertical-align: top; background-color: rgb(228, 247, 210); color: rgb(38, 38, 38); min-width: 90px; font-size: 14px; white-space: normal; overflow-wrap: break-word; border: 1px solid rgb(217, 217, 217); padding: 4px 8px; cursor: default;\"><p style=\"font-size: 14px; color: rgb(38, 38, 38); line-height: 24px; letter-spacing: 0.05em; outline-style: none; overflow-wrap: break-word; margin: 0px;\">8.1</p></td><td colspan=\"1\" style=\"vertical-align: top; background-color: rgb(82, 196, 26); color: rgb(38, 38, 38); min-width: 90px; font-size: 14px; white-space: normal; overflow-wrap: break-word; border: 1px solid rgb(217, 217, 217); padding: 4px 8px; cursor: default;\"><p style=\"font-size: 14px; color: rgb(38, 38, 38); line-height: 24px; letter-spacing: 0.05em; outline-style: none; overflow-wrap: break-word; margin: 0px;\"><strong><span style=\"color: #FFFFFF;\">我的评分</span></strong></p></td><td colspan=\"1\" style=\"vertical-align: top; background-color: rgb(228, 247, 210); color: rgb(38, 38, 38); min-width: 90px; font-size: 14px; white-space: normal; overflow-wrap: break-word; border: 1px solid rgb(217, 217, 217); padding: 4px 8px; cursor: default;\"><p style=\"font-size: 14px; color: rgb(38, 38, 38); line-height: 24px; letter-spacing: 0.05em; outline-style: none; overflow-wrap: break-word; margin: 0px;\">☆☆☆☆</p></td></tr></tbody></table></div><p style=\"font-size: 14px; color: rgb(38, 38, 38); line-height: 24px; letter-spacing: 0.05em; outline-style: none; overflow-wrap: break-word; margin: 0px;\"><br></p><h4 id=\"uLRxc\" style=\"padding: 7px 0px; margin: 0px; font-weight: 700; font-size: 16px; line-height: 24px;\">内容简介</h4><p style=\"font-size: 14px; color: rgb(38, 38, 38); line-height: 24px; letter-spacing: 0.05em; outline-style: none; overflow-wrap: break-word; margin: 0px;\"><span class=\"lake-fontsize-11\" style=\"color: rgb(140, 140, 140); background-color: transparent; font-size: 14px; line-height: 24px;\" data-mce-style=\"font-size: 11px\"><span>在此处输入文本</span></span></p><p style=\"font-size: 14px; color: rgb(38, 38, 38); line-height: 24px; letter-spacing: 0.05em; outline-style: none; overflow-wrap: break-word; margin: 0px;\"><span style=\"color: #BFBFBF;\">你将读到的是北野武的出身、父母、兄弟和家庭的故事。</span></p><p style=\"font-size: 14px; color: rgb(38, 38, 38); line-height: 24px; letter-spacing: 0.05em; outline-style: none; overflow-wrap: break-word; margin: 0px;\"><span style=\"color: #BFBFBF;\">但请放心，这绝非一个自我感觉良好的人写的那种“优良课外读物”。</span></p><p style=\"font-size: 14px; color: rgb(38, 38, 38); line-height: 24px; letter-spacing: 0.05em; outline-style: none; overflow-wrap: break-word; margin: 0px;\"><span style=\"color: #BFBFBF;\">相反，北野武用搞笑到甚至刻薄方式描绘这些人和事，让我们在笑与泪的交织中，看到真情和真实，看到那么多情、柔软的心。</span></p><p style=\"font-size: 14px; color: rgb(38, 38, 38); line-height: 24px; letter-spacing: 0.05em; outline-style: none; overflow-wrap: break-word; margin: 0px;\"><span style=\"color: #BFBFBF;\"><br></span></p><h4 id=\"E9053\" style=\"padding: 7px 0px; margin: 0px; font-weight: 700; font-size: 16px; line-height: 24px;\">书摘</h4><p style=\"font-size: 14px; color: rgb(38, 38, 38); line-height: 24px; letter-spacing: 0.05em; outline-style: none; overflow-wrap: break-word; margin: 0px;\"><span class=\"lake-fontsize-11\" style=\"color: rgb(140, 140, 140); background-color: transparent; font-size: 14px; line-height: 24px;\" data-mce-style=\"font-size: 11px\"><span>在此处输入文本</span></span></p><ul lake-indent=\"0\" style=\"list-style-type: disc; margin: 0px; padding-left: 23px; font-size: 14px; color: rgb(38, 38, 38); line-height: 24px; letter-spacing: 0.05em; outline-style: none; overflow-wrap: break-word;\"><li><span style=\"color: #BFBFBF;\">你将读到的是北野武的出身、父母、兄弟和家庭的故事。</span></li><li><span style=\"color: #BFBFBF;\">但请放心，这绝非一个自我感觉良好的人写的那种“优良课外读物”。<span data-card-type=\"inline\" data-lake-card=\"label\"><span class=\"lake-card-label-container\" draggable=\"true\" style=\"background: rgb(255, 232, 230); color: rgb(130, 0, 20); opacity: 1; cursor: pointer; user-select: none; font-weight: 400; font-size: 12px; overflow: hidden; max-width: 200px; display: inline-block; white-space: nowrap; margin-bottom: -4px; border-radius: 4px; border: none; padding: 2px 5px; text-overflow: ellipsis; line-height: 14px; margin-left: 1px; margin-right: 1px;\">很喜欢这句</span></span></span><span style=\"color: #52C41A;\"><span>←方便打标签的状态卡片</span></span></li><li><span style=\"color: #BFBFBF;\">相反，北野武用搞笑到甚至刻薄方式描绘这些人和事，让我们在笑与泪的交织中，看到真情和真实，看到那么多情、柔软的心。</span></li></ul><p style=\"font-size: 14px; color: rgb(38, 38, 38); line-height: 24px; letter-spacing: 0.05em; outline-style: none; overflow-wrap: break-word; margin: 0px;\"><br></p><h4 id=\"vEdHo\" style=\"padding: 7px 0px; margin: 0px; font-weight: 700; font-size: 16px; line-height: 24px;\">读后感</h4><p style=\"font-size: 14px; color: rgb(38, 38, 38); line-height: 24px; letter-spacing: 0.05em; outline-style: none; overflow-wrap: break-word; margin: 0px;\"><span class=\"lake-fontsize-11\" style=\"color: rgb(140, 140, 140); background-color: transparent; font-size: 14px; line-height: 24px;\" data-mce-style=\"font-size: 11px\"><span>在此处输入文本</span></span></p><ul lake-indent=\"0\" style=\"list-style-type: disc; margin: 0px; padding-left: 23px; font-size: 14px; color: rgb(38, 38, 38); line-height: 24px; letter-spacing: 0.05em; outline-style: none; overflow-wrap: break-word;\"><li><span style=\"color: #BFBFBF;\">你将读到的是北野武的出身、父母、兄弟和家庭的故事。</span></li><li><span style=\"color: #BFBFBF;\">但请放心，这绝非一个自我感觉良好的人写的那种“优良课外读物”。</span></li><li><span style=\"color: #BFBFBF;\">相反，北野武用搞笑到甚至刻薄方式描绘这些人和事，让我们在笑与泪的交织中，看到真情和真实，看到那么多情、柔软的心。</span></li></ul></div>",
    "body_lake": "<!doctype lake><meta name=\"doc-version\" content=\"1\" /><h4 id=\"30e8c\" style=\"text-align: center;\"><card type=\"inline\" name=\"image\" value=\"data:%7B%22src%22%3A%22https%3A%2F%2Fcdn.nlark.com%2Fyuque%2F0%2F2019%2Fpng%2F215718%2F1567507815646-d739438a-8ffd-4107-9d87-130e2104446a.png%22%2C%22originWidth%22%3A1080%2C%22originHeight%22%3A1553%2C%22name%22%3A%22image.png%22%2C%22size%22%3A367334%2C%22display%22%3A%22inline%22%2C%22align%22%3A%22left%22%2C%22linkTarget%22%3A%22_blank%22%2C%22status%22%3A%22done%22%2C%22search%22%3A%22%22%2C%22width%22%3A161%2C%22height%22%3A232%7D\"></card></h4><p style=\"text-align: center;\"><span style=\"color: #8C8C8C;\"><em><span>插入封面图片，点击图片，设置图片大小</span></em></span></p><h4 id=\"K3ibk\" style=\"text-align: left;\">关于本书</h4><p><span style=\"color: #8C8C8C;\"><span>插入「表格</span></span><span style=\"color: #8C8C8C;\"><span>」</span></span></p><card type=\"block\" name=\"table\" value=\"data:%7B%22rows%22%3A3%2C%22cols%22%3A4%2C%22html%22%3A%22%3Ctable%20class%3D%5C%22lake-table%5C%22%20style%3D%5C%22width%3A%20695px%3B%5C%22%3E%3Ccolgroup%3E%3Ccol%20width%3D%5C%2280%5C%22%20span%3D%5C%221%5C%22%20%2F%3E%3Ccol%20width%3D%5C%22285%5C%22%20span%3D%5C%221%5C%22%20%2F%3E%3Ccol%20width%3D%5C%2291%5C%22%20span%3D%5C%221%5C%22%20%2F%3E%3Ccol%20width%3D%5C%22238%5C%22%20span%3D%5C%221%5C%22%20%2F%3E%3C%2Fcolgroup%3E%3Ctbody%3E%3Ctr%20style%3D%5C%22height%3A%2033px%3B%5C%22%3E%3Ctd%20style%3D%5C%22background-color%3A%20%2352C41A%3B%5C%22%3E%3Cspan%20style%3D%5C%22color%3A%20%23FFFFFF%3B%5C%22%3E%3Cstrong%3E%E4%B9%A6%E5%90%8D%3C%2Fstrong%3E%3C%2Fspan%3E%3C%2Ftd%3E%3Ctd%20style%3D%5C%22background-color%3A%20%23E4F7D2%3B%5C%22%3E%3Cp%3E%3Ca%20href%3D%5C%22https%3A%2F%2Fbook.douban.com%2Fsubject%2F25944034%2F%5C%22%20target%3D%5C%22_blank%5C%22%3E%E3%80%8A%E8%8F%8A%E6%AC%A1%E9%83%8E%E4%B8%8E%E4%BD%90%E7%BA%AA%E3%80%8B%3C%2Fa%3E%3C%2Fp%3E%3C%2Ftd%3E%3Ctd%20style%3D%5C%22background-color%3A%20%2352C41A%3B%5C%22%3E%3Cspan%20style%3D%5C%22color%3A%20%23FFFFFF%3B%5C%22%3E%3Cstrong%3E%E4%BD%9C%E8%80%85%3C%2Fstrong%3E%3C%2Fspan%3E%3C%2Ftd%3E%3Ctd%20rowspan%3D%5C%221%5C%22%20style%3D%5C%22background-color%3A%20%23E4F7D2%3B%5C%22%3E%3Cp%3E%E5%8C%97%E9%87%8E%E6%AD%A6%3Ccard%20type%3D%5C%22inline%5C%22%20name%3D%5C%22label%5C%22%20value%3D%5C%22data%3A%257B%2522label%2522%253A%2522%25E6%2597%25A5%25E6%259C%25AC%2522%252C%2522colorIndex%2522%253A4%257D%5C%22%3E%3C%2Fcard%3E%3C%2Fp%3E%3C%2Ftd%3E%3C%2Ftr%3E%3Ctr%20style%3D%5C%22height%3A%2033px%3B%5C%22%3E%3Ctd%20style%3D%5C%22vertical-align%3A%20top%3B%20background-color%3A%20%2352C41A%3B%20color%3A%20%23262626%3B%5C%22%3E%3Cp%3E%3Cspan%20style%3D%5C%22color%3A%20%23FFFFFF%3B%5C%22%3E%3Cstrong%3E%E5%87%BA%E7%89%88%E7%A4%BE%3C%2Fstrong%3E%3C%2Fspan%3E%3C%2Fp%3E%3C%2Ftd%3E%3Ctd%20style%3D%5C%22background-color%3A%20%23E4F7D2%3B%5C%22%3E%3Cp%3E%3Cspan%20class%3D%5C%22lake-fontsize-10%5C%22%3E%E8%AF%91%E6%9E%97%E5%87%BA%E7%89%88%E7%A4%BE%3C%2Fspan%3E%3C%2Fp%3E%3C%2Ftd%3E%3Ctd%20style%3D%5C%22background-color%3A%20%2352C41A%3B%5C%22%3E%3Cp%3E%3Cspan%20style%3D%5C%22color%3A%20%23FFFFFF%3B%5C%22%3E%3Cstrong%3E%E9%98%85%E8%AF%BB%E6%97%A5%E6%9C%9F%3C%2Fstrong%3E%3C%2Fspan%3E%3C%2Fp%3E%3C%2Ftd%3E%3Ctd%20rowspan%3D%5C%221%5C%22%20style%3D%5C%22vertical-align%3A%20top%3B%20background-color%3A%20%23E4F7D2%3B%20color%3A%20%23262626%3B%5C%22%3E%3Cp%3E2019%E5%B9%B42%E6%9C%88%3C%2Fp%3E%3C%2Ftd%3E%3C%2Ftr%3E%3Ctr%20style%3D%5C%22height%3A%2033px%3B%5C%22%3E%3Ctd%20colspan%3D%5C%221%5C%22%20style%3D%5C%22vertical-align%3A%20top%3B%20background-color%3A%20%2352C41A%3B%20color%3A%20%23262626%3B%5C%22%3E%3Cp%3E%3Cspan%20style%3D%5C%22color%3A%20%23FFFFFF%3B%5C%22%3E%3Cstrong%3E%E8%B1%86%E7%93%A3%E8%AF%84%E5%88%86%3C%2Fstrong%3E%3C%2Fspan%3E%3C%2Fp%3E%3C%2Ftd%3E%3Ctd%20colspan%3D%5C%221%5C%22%20style%3D%5C%22vertical-align%3A%20top%3B%20background-color%3A%20%23E4F7D2%3B%20color%3A%20%23262626%3B%5C%22%3E%3Cp%3E8.1%3C%2Fp%3E%3C%2Ftd%3E%3Ctd%20colspan%3D%5C%221%5C%22%20style%3D%5C%22vertical-align%3A%20top%3B%20background-color%3A%20%2352C41A%3B%20color%3A%20%23262626%3B%5C%22%3E%3Cp%3E%3Cstrong%3E%3Cspan%20style%3D%5C%22color%3A%20%23FFFFFF%3B%5C%22%3E%E6%88%91%E7%9A%84%E8%AF%84%E5%88%86%3C%2Fspan%3E%3C%2Fstrong%3E%3C%2Fp%3E%3C%2Ftd%3E%3Ctd%20colspan%3D%5C%221%5C%22%20style%3D%5C%22vertical-align%3A%20top%3B%20background-color%3A%20%23E4F7D2%3B%20color%3A%20%23262626%3B%5C%22%3E%3Cp%3E%E2%98%86%E2%98%86%E2%98%86%E2%98%86%3C%2Fp%3E%3C%2Ftd%3E%3C%2Ftr%3E%3C%2Ftbody%3E%3C%2Ftable%3E%22%2C%22id%22%3A%22yE9oY%22%7D\"></card><p><br /></p><h4 id=\"uLRxc\">内容简介</h4><p><span class=\"lake-fontsize-11\" style=\"color: #8C8C8C; background-color: transparent;\"><span>在此处输入文本</span></span></p><p><span style=\"color: #BFBFBF;\">你将读到的是北野武的出身、父母、兄弟和家庭的故事。</span></p><p><span style=\"color: #BFBFBF;\">但请放心，这绝非一个自我感觉良好的人写的那种“优良课外读物”。</span></p><p><span style=\"color: #BFBFBF;\">相反，北野武用搞笑到甚至刻薄方式描绘这些人和事，让我们在笑与泪的交织中，看到真情和真实，看到那么多情、柔软的心。</span></p><p><span style=\"color: #BFBFBF;\"><br /></span></p><h4 id=\"E9053\">书摘</h4><p><span class=\"lake-fontsize-11\" style=\"color: #8C8C8C; background-color: transparent;\"><span>在此处输入文本</span></span></p><ul><li><span style=\"color: #BFBFBF;\">你将读到的是北野武的出身、父母、兄弟和家庭的故事。</span></li><li><span style=\"color: #BFBFBF;\">但请放心，这绝非一个自我感觉良好的人写的那种“优良课外读物”。<card type=\"inline\" name=\"label\" value=\"data:%7B%22label%22%3A%22%E5%BE%88%E5%96%9C%E6%AC%A2%E8%BF%99%E5%8F%A5%22%2C%22colorIndex%22%3A0%7D\"></card></span><span style=\"color: #52C41A;\"><span>←方便打标签的状态卡片</span></span></li><li><span style=\"color: #BFBFBF;\">相反，北野武用搞笑到甚至刻薄方式描绘这些人和事，让我们在笑与泪的交织中，看到真情和真实，看到那么多情、柔软的心。</span></li></ul><p><br /></p><h4 id=\"vEdHo\">读后感</h4><p><span class=\"lake-fontsize-11\" style=\"color: #8C8C8C; background-color: transparent;\"><span>在此处输入文本</span></span></p><ul><li><span style=\"color: #BFBFBF;\">你将读到的是北野武的出身、父母、兄弟和家庭的故事。</span></li><li><span style=\"color: #BFBFBF;\">但请放心，这绝非一个自我感觉良好的人写的那种“优良课外读物”。</span></li><li><span style=\"color: #BFBFBF;\">相反，北野武用搞笑到甚至刻薄方式描绘这些人和事，让我们在笑与泪的交织中，看到真情和真实，看到那么多情、柔软的心。</span></li></ul>",
    "body_draft_lake": "<!doctype lake><meta name=\"doc-version\" content=\"1\" /><meta name=\"viewport\" content=\"fixed\" /><meta name=\"typography\" content=\"traditional\" /><h4 id=\"30e8c\" data-lake-id=\"1f5abb93fdf0e6ec69b036e75246859d_h4_0\" style=\"text-align: center;\"><card type=\"inline\" name=\"image\" value=\"data:%7B%22src%22%3A%22https%3A%2F%2Fcdn.nlark.com%2Fyuque%2F0%2F2019%2Fpng%2F215718%2F1567507815646-d739438a-8ffd-4107-9d87-130e2104446a.png%22%2C%22originWidth%22%3A1080%2C%22originHeight%22%3A1553%2C%22name%22%3A%22image.png%22%2C%22size%22%3A367334%2C%22display%22%3A%22inline%22%2C%22align%22%3A%22left%22%2C%22linkTarget%22%3A%22_blank%22%2C%22status%22%3A%22done%22%2C%22style%22%3A%22none%22%2C%22search%22%3A%22%22%2C%22margin%22%3A%7B%22top%22%3Afalse%2C%22bottom%22%3Afalse%7D%2C%22width%22%3A161%2C%22height%22%3A232%7D\"></card></h4><p data-lake-id=\"36b3f930335de8c65192d3bd46da29dc_p_0\" style=\"text-align: center;\"><span style=\"color: #8C8C8C;\"><em><span>插入封面图片，点击图片，设置图片大小</span></em></span></p><h4 id=\"K3ibk\" data-lake-id=\"1768d8938ea5bbc679f5d510410d77f0_h4_1\" style=\"text-align: left;\">关于本书</h4><p data-lake-id=\"70eb829ea1151f0f11f7672346169c4e_p_1\"><span style=\"color: #8C8C8C;\"><span>插入「表格</span></span><span style=\"color: #8C8C8C;\"><span>」</span></span></p><card type=\"block\" name=\"table\" value=\"data:%7B%22rows%22%3A3%2C%22cols%22%3A4%2C%22html%22%3A%22%3Ctable%20class%3D%5C%22lake-table%5C%22%20style%3D%5C%22width%3A%20694px%3B%5C%22%3E%3Ccolgroup%3E%3Ccol%20width%3D%5C%2280%5C%22%20span%3D%5C%221%5C%22%20%2F%3E%3Ccol%20width%3D%5C%22285%5C%22%20span%3D%5C%221%5C%22%20%2F%3E%3Ccol%20width%3D%5C%2291%5C%22%20span%3D%5C%221%5C%22%20%2F%3E%3Ccol%20width%3D%5C%22238%5C%22%20span%3D%5C%221%5C%22%20%2F%3E%3C%2Fcolgroup%3E%3Ctbody%3E%3Ctr%20style%3D%5C%22height%3A%2033px%3B%5C%22%3E%3Ctd%20style%3D%5C%22background-color%3A%20%2352C41A%3B%5C%22%3E%3Cspan%20style%3D%5C%22color%3A%20%23FFFFFF%3B%5C%22%3E%3Cstrong%3E%E4%B9%A6%E5%90%8D%3C%2Fstrong%3E%3C%2Fspan%3E%3C%2Ftd%3E%3Ctd%20style%3D%5C%22background-color%3A%20%23E4F7D2%3B%5C%22%3E%3Cp%20data-lake-id%3D%5C%2205af1c874e710ee9fee71881d9b8349d%5C%22%3E%3Ca%20href%3D%5C%22https%3A%2F%2Fbook.douban.com%2Fsubject%2F25944034%2F%5C%22%20target%3D%5C%22_blank%5C%22%3E%E3%80%8A%E8%8F%8A%E6%AC%A1%E9%83%8E%E4%B8%8E%E4%BD%90%E7%BA%AA%E3%80%8B%3C%2Fa%3E%3C%2Fp%3E%3C%2Ftd%3E%3Ctd%20style%3D%5C%22background-color%3A%20%2352C41A%3B%5C%22%3E%3Cspan%20style%3D%5C%22color%3A%20%23FFFFFF%3B%5C%22%3E%3Cstrong%3E%E4%BD%9C%E8%80%85%3C%2Fstrong%3E%3C%2Fspan%3E%3C%2Ftd%3E%3Ctd%20rowspan%3D%5C%221%5C%22%20style%3D%5C%22background-color%3A%20%23E4F7D2%3B%5C%22%3E%3Cp%20data-lake-id%3D%5C%22db668e08ea2d6ef77c24879170730cdc%5C%22%3E%E5%8C%97%E9%87%8E%E6%AD%A6%3Ccard%20type%3D%5C%22inline%5C%22%20name%3D%5C%22label%5C%22%20value%3D%5C%22data%3A%257B%2522label%2522%253A%2522%25E6%2597%25A5%25E6%259C%25AC%2522%252C%2522colorIndex%2522%253A4%257D%5C%22%3E%3C%2Fcard%3E%3C%2Fp%3E%3C%2Ftd%3E%3C%2Ftr%3E%3Ctr%20style%3D%5C%22height%3A%2033px%3B%5C%22%3E%3Ctd%20style%3D%5C%22vertical-align%3A%20top%3B%20background-color%3A%20%2352C41A%3B%20color%3A%20%23262626%3B%5C%22%3E%3Cp%20data-lake-id%3D%5C%224e5a0636ecbf65623e20c542c2cd0bb6%5C%22%3E%3Cspan%20style%3D%5C%22color%3A%20%23FFFFFF%3B%5C%22%3E%3Cstrong%3E%E5%87%BA%E7%89%88%E7%A4%BE%3C%2Fstrong%3E%3C%2Fspan%3E%3C%2Fp%3E%3C%2Ftd%3E%3Ctd%20style%3D%5C%22background-color%3A%20%23E4F7D2%3B%5C%22%3E%3Cp%20data-lake-id%3D%5C%22928c55f801e825b37ef1807a14a109a3%5C%22%3E%3Cspan%20class%3D%5C%22lake-fontsize-10%5C%22%3E%E8%AF%91%E6%9E%97%E5%87%BA%E7%89%88%E7%A4%BE%3C%2Fspan%3E%3C%2Fp%3E%3C%2Ftd%3E%3Ctd%20style%3D%5C%22background-color%3A%20%2352C41A%3B%5C%22%3E%3Cp%20data-lake-id%3D%5C%22c647db30f124284316607b5c3cc2ee75%5C%22%3E%3Cspan%20style%3D%5C%22color%3A%20%23FFFFFF%3B%5C%22%3E%3Cstrong%3E%E9%98%85%E8%AF%BB%E6%97%A5%E6%9C%9F%3C%2Fstrong%3E%3C%2Fspan%3E%3C%2Fp%3E%3C%2Ftd%3E%3Ctd%20rowspan%3D%5C%221%5C%22%20style%3D%5C%22vertical-align%3A%20top%3B%20background-color%3A%20%23E4F7D2%3B%20color%3A%20%23262626%3B%5C%22%3E%3Cp%20data-lake-id%3D%5C%22578a44c6710e51d81353d8a666507571%5C%22%3E2019%E5%B9%B42%E6%9C%88%3C%2Fp%3E%3C%2Ftd%3E%3C%2Ftr%3E%3Ctr%20style%3D%5C%22height%3A%2033px%3B%5C%22%3E%3Ctd%20colspan%3D%5C%221%5C%22%20style%3D%5C%22vertical-align%3A%20top%3B%20background-color%3A%20%2352C41A%3B%20color%3A%20%23262626%3B%5C%22%3E%3Cp%20data-lake-id%3D%5C%22508e316e268007d7338129137e2af5eb%5C%22%3E%3Cspan%20style%3D%5C%22color%3A%20%23FFFFFF%3B%5C%22%3E%3Cstrong%3E%E8%B1%86%E7%93%A3%E8%AF%84%E5%88%86%3C%2Fstrong%3E%3C%2Fspan%3E%3C%2Fp%3E%3C%2Ftd%3E%3Ctd%20colspan%3D%5C%221%5C%22%20style%3D%5C%22vertical-align%3A%20top%3B%20background-color%3A%20%23E4F7D2%3B%20color%3A%20%23262626%3B%5C%22%3E%3Cp%20data-lake-id%3D%5C%224a978719fccd8adb3d49a10a143e48b0%5C%22%3E8.1%3C%2Fp%3E%3C%2Ftd%3E%3Ctd%20colspan%3D%5C%221%5C%22%20style%3D%5C%22vertical-align%3A%20top%3B%20background-color%3A%20%2352C41A%3B%20color%3A%20%23262626%3B%5C%22%3E%3Cp%20data-lake-id%3D%5C%22f05d8b4fb262b0aae7f962a33b7c2716%5C%22%3E%3Cstrong%3E%3Cspan%20style%3D%5C%22color%3A%20%23FFFFFF%3B%5C%22%3E%E6%88%91%E7%9A%84%E8%AF%84%E5%88%86%3C%2Fspan%3E%3C%2Fstrong%3E%3C%2Fp%3E%3C%2Ftd%3E%3Ctd%20colspan%3D%5C%221%5C%22%20style%3D%5C%22vertical-align%3A%20top%3B%20background-color%3A%20%23E4F7D2%3B%20color%3A%20%23262626%3B%5C%22%3E%3Cp%20data-lake-id%3D%5C%2237f5a400bd71ba91500ed5410822e430%5C%22%3E%E2%98%86%E2%98%86%E2%98%86%E2%98%86%3C%2Fp%3E%3C%2Ftd%3E%3C%2Ftr%3E%3C%2Ftbody%3E%3C%2Ftable%3E%22%2C%22margin%22%3Afalse%2C%22id%22%3A%22yE9oY%22%7D\"></card><p data-lake-id=\"2b2b3e7dc122d1502f582c0c8b7958d8_p_2\"><br /></p><h4 id=\"uLRxc\" data-lake-id=\"ec2cbba4b6da1adc4a42d204738c2782_h4_2\">内容简介</h4><p data-lake-id=\"aa6e99b0ea35459f949be43c3dba587f_p_3\"><span class=\"lake-fontsize-11\" style=\"color: #8C8C8C; background-color: transparent;\"><span>在此处输入文本</span></span></p><p data-lake-id=\"5b584d86eaef942c012bb06a4e2f69ad_p_4\"><span style=\"color: #BFBFBF;\">你将读到的是北野武的出身、父母、兄弟和家庭的故事。</span></p><p data-lake-id=\"77bd9cb3dad8dbe30cbc496d0177ddd0_p_5\"><span style=\"color: #BFBFBF;\">但请放心，这绝非一个自我感觉良好的人写的那种“优良课外读物”。</span></p><p data-lake-id=\"7a7f76face1ffff003ea1295cdd13727_p_6\"><span style=\"color: #BFBFBF;\">相反，北野武用搞笑到甚至刻薄方式描绘这些人和事，让我们在笑与泪的交织中，看到真情和真实，看到那么多情、柔软的心。</span></p><p data-lake-id=\"e1b0979b54c1fb29acc1d92ad2159922_p_7\"><span style=\"color: #BFBFBF;\"><br /></span></p><h4 id=\"E9053\" data-lake-id=\"467f15c436bb9f5ee26c396b6491f819_h4_3\">书摘</h4><p data-lake-id=\"8ff0fd4af909cf8f49c90de996998c1c_p_8\"><span class=\"lake-fontsize-11\" style=\"color: #8C8C8C; background-color: transparent;\"><span>在此处输入文本</span></span></p><ul data-lake-id=\"ce1f3ecf960b67c09d7beb096afc58b9_ul_0\"><li data-lake-id=\"484a4eb61edb42fd3a0435c833d6c134_li_0\"><span style=\"color: #BFBFBF;\">你将读到的是北野武的出身、父母、兄弟和家庭的故事。</span></li><li data-lake-id=\"14e8b06282c4b3ffa13df416983a3d74_li_1\"><span style=\"color: #BFBFBF;\">但请放心，这绝非一个自我感觉良好的人写的那种“优良课外读物”。<card type=\"inline\" name=\"label\" value=\"data:%7B%22label%22%3A%22%E5%BE%88%E5%96%9C%E6%AC%A2%E8%BF%99%E5%8F%A5%22%2C%22colorIndex%22%3A0%7D\"></card></span><span style=\"color: #52C41A;\"><span>←方便打标签的状态卡片</span></span></li><li data-lake-id=\"4fef7d50126dc0f05d45aaf544f7ef5e_li_2\"><span style=\"color: #BFBFBF;\">相反，北野武用搞笑到甚至刻薄方式描绘这些人和事，让我们在笑与泪的交织中，看到真情和真实，看到那么多情、柔软的心。</span></li></ul><p data-lake-id=\"eadc4ec477465f1f239730d987d394b1_p_9\"><br /></p><h4 id=\"vEdHo\" data-lake-id=\"f806f5c4b4ab22548bf03f1f0fb69508_h4_4\">读后感</h4><p data-lake-id=\"f3e3475a2a0945cc7db66d404d229831_p_10\"><span class=\"lake-fontsize-11\" style=\"color: #8C8C8C; background-color: transparent;\"><span>在此处输入文本</span></span></p><ul data-lake-id=\"341dc8b4225e7747645a17c8dec1c96b_ul_1\"><li data-lake-id=\"e20057bdc539c61cc1bf2003e64d7bbd_li_3\"><span style=\"color: #BFBFBF;\">你将读到的是北野武的出身、父母、兄弟和家庭的故事。</span></li><li data-lake-id=\"838a056d809b374cfaab0a0c7c63ac63_li_4\"><span style=\"color: #BFBFBF;\">但请放心，这绝非一个自我感觉良好的人写的那种“优良课外读物”。</span></li><li data-lake-id=\"a15a18b249bf3c6f8c3f354bb23a2aee_li_5\"><span style=\"color: #BFBFBF;\">相反，北野武用搞笑到甚至刻薄方式描绘这些人和事，让我们在笑与泪的交织中，看到真情和真实，看到那么多情、柔软的心。</span></li></ul>",
    "public": 1,
    "status": 0,
    "view_status": 0,
    "read_status": 1,
    "likes_count": 0,
    "comments_count": 0,
    "content_updated_at": "2020-05-26T06:41:47.000Z",
    "deleted_at": null,
    "created_at": "2020-04-29T01:41:14.000Z",
    "updated_at": "2020-05-26T10:25:51.000Z",
    "published_at": "2020-04-29T01:41:14.000Z",
    "first_published_at": "2020-04-29T01:41:14.000Z",
    "word_count": 0,
    "cover": "https://cdn.nlark.com/yuque/0/2019/png/215718/1567507815646-d739438a-8ffd-4107-9d87-130e2104446a.png",
    "description": "插入封面图片，点击图片，设置图片大小关于本书插入「表格」书名《菊次郎与佐纪》作者北野武日本出版社译林出版社阅读日期2019年2月豆瓣评分8.1我的评分☆☆☆☆内容简介在此处输入文本你将读到的是北野武的出身、父母、兄弟和家庭的故事。但请放心，这绝非一个自我感觉良好的人写的那种“优良课外读物”。相...",
    "custom_description": null,
    "hits": 0,
    "_serializer": "v2.doc_detail"
  }
]